docs/_config.yml
docs/index.md
docs/_includes/head-custom.html
docs/assets/Owl Colossogram (owl_TAG4learSOAEwf1).png
docs/assets/Owl N_xi Fit [9633Hz] (owl_TAG4learSOAEwf1).png
docs/assets/logo.png
examples/example_main.py
examples/example_zeta_windowing.py
phaseco/__init__.py
phaseco/funcs.py
phaseco/helper_funcs.py
phaseco/plots.py
phaseco-1.0.0.dist-info/licenses/LICENSE.txt
phaseco-1.0.0.dist-info/METADATA
phaseco-1.0.0.dist-info/WHEEL
phaseco-1.0.0.dist-info/top_level.txt
phaseco-1.0.0.dist-info/RECORD
