Metadata-Version: 2.4
Name: phaseco
Version: 1.0.0
Summary: Tools for phase autocoherence analysis with dynamic windowing methods
Author-email: "Seth N.S. Peacock" <seththepeacock@gmail.com>
License-Expression: MIT
Project-URL: Homepage, https://seththepeacock.github.io/phaseco
Project-URL: Repository, https://github.com/seththepeacock/phaseco
Project-URL: Documentation, https://seththepeacock.github.io/phaseco
Requires-Python: >=3.8
License-File: LICENSE.txt
Requires-Dist: numpy
Requires-Dist: scipy
Requires-Dist: matplotlib
Requires-Dist: tqdm
Dynamic: license-file
